README
setup.py
bin/bu
bu/__init__.py
bu/errors.py
bu/execute.py
bu/main.py
bu/model.py
bu/output.py
bu/parsing.py
bu/preproc.py
bu.egg-info/PKG-INFO
bu.egg-info/SOURCES.txt
bu.egg-info/dependency_links.txt
bu.egg-info/entry_points.txt
bu.egg-info/requires.txt
bu.egg-info/top_level.txt
bu/actions/__init__.py
bu/actions/py_action.py
bu/actions/sh_action.py
bu/lib/__init__.py
bu/tools/__init__.py
bu/tools/bupygments.py
bu/tools/busphinx.py