Metadata-Version: 1.0
Name: bu
Version: 0.1
Summary: Build Utilities, a microscopic build system.
Home-page: http://packages.python.org/bu
Author: Ali Afshar
Author-email: aafshar@gmail.com
License: GPLv3
Platform: UNKNOWN
